LICENSE
MANIFEST.in
README.rst
setup.py
tox.ini
lemon_robots.egg-info/PKG-INFO
lemon_robots.egg-info/SOURCES.txt
lemon_robots.egg-info/dependency_links.txt
lemon_robots.egg-info/requires.txt
lemon_robots.egg-info/top_level.txt
robots/__init__.py
robots/admin.py
robots/models.py
robots/tests.py
robots/urls.py
robots/views.py
robots/locale/ru/LC_MESSAGES/django.mo
robots/locale/ru/LC_MESSAGES/django.po
robots/migrations/0001_initial.py
robots/migrations/__init__.py
robots/templates/robots/robots.txt
tests/__init__.py
tests/runtests.sh
tests/settings.py
tests/settings_django_admin.py
tests/settings_lemon_admin.py
tests/settings_views.py
tests/urls.py
tests/test_django_admin/__init__.py
tests/test_django_admin/models.py
tests/test_django_admin/tests.py
tests/test_django_admin/urls.py
tests/test_lemon_admin/__init__.py
tests/test_lemon_admin/models.py
tests/test_lemon_admin/tests.py
tests/test_lemon_admin/urls.py
tests/test_views/__init__.py
tests/test_views/models.py
tests/test_views/tests.py